sclik/app/__init__.py
sclik/app/ipfs_setup_handler.py
sclik/app/main.py
sclik-0.1.13.dist-info/licenses/LICENSE
sclik-0.1.13.dist-info/METADATA
sclik-0.1.13.dist-info/WHEEL
sclik-0.1.13.dist-info/entry_points.txt
sclik-0.1.13.dist-info/top_level.txt
sclik-0.1.13.dist-info/RECORD
