Metadata-Version: 2.4
Name: sclik
Version: 0.1.13
Summary: A decentralized terminal social network using IPFS.
Author-email: Ryan Gerard Wilson <ryan@wilsonfamilyoffice.com>
License: MIT License
Project-URL: Homepage, https://github.com/yourusername/sclik
Project-URL: Issues, https://github.com/yourusername/sclik/issues
Classifier: Programming Language :: Python :: 3
Classifier: License :: OSI Approved :: MIT License
Classifier: Operating System :: OS Independent
Requires-Python: >=3.6
License-File: LICENSE
Dynamic: license-file
